.version_full
COPYING
README.md
setup.py
bin/lottie_cat.py
bin/lottie_convert.py
bin/lottie_diagnostic.py
bin/lottie_diff.py
bin/lottie_fonts.py
bin/lottie_printcolor.py
bin/raster_palette.py
bin/tgs_check.py
lib/lottie/__init__.py
lib/lottie/nvector.py
lib/lottie/version.py
lib/lottie.egg-info/PKG-INFO
lib/lottie.egg-info/SOURCES.txt
lib/lottie.egg-info/dependency_links.txt
lib/lottie.egg-info/requires.txt
lib/lottie.egg-info/top_level.txt
lib/lottie.egg-info/zip-safe
lib/lottie/exporters/__init__.py
lib/lottie/exporters/base.py
lib/lottie/exporters/cairo.py
lib/lottie/exporters/core.py
lib/lottie/exporters/dot_lottie.py
lib/lottie/exporters/gif.py
lib/lottie/exporters/pretty_print.py
lib/lottie/exporters/sif.py
lib/lottie/exporters/svg.py
lib/lottie/exporters/tgs_validator.py
lib/lottie/exporters/video.py
lib/lottie/gui/__init__.py
lib/lottie/gui/console.py
lib/lottie/gui/import_export.py
lib/lottie/gui/search_widget.py
lib/lottie/gui/timeline_widget.py
lib/lottie/gui/tree_view.py
lib/lottie/importers/__init__.py
lib/lottie/importers/__mattbas_opentoons.py
lib/lottie/importers/aep.py
lib/lottie/importers/base.py
lib/lottie/importers/core.py
lib/lottie/importers/dot_lottie.py
lib/lottie/importers/krita.py
lib/lottie/importers/raster.py
lib/lottie/importers/script.py
lib/lottie/importers/sif.py
lib/lottie/importers/svg.py
lib/lottie/objects/__init__.py
lib/lottie/objects/animation.py
lib/lottie/objects/assets.py
lib/lottie/objects/base.py
lib/lottie/objects/bezier.py
lib/lottie/objects/composition.py
lib/lottie/objects/easing.py
lib/lottie/objects/effects.py
lib/lottie/objects/enums.py
lib/lottie/objects/helpers.py
lib/lottie/objects/layers.py
lib/lottie/objects/properties.py
lib/lottie/objects/shapes.py
lib/lottie/objects/styles.py
lib/lottie/objects/text.py
lib/lottie/parsers/__init__.py
lib/lottie/parsers/baseporter.py
lib/lottie/parsers/glaxnimate_helpers.py
lib/lottie/parsers/pixel.py
lib/lottie/parsers/raster.py
lib/lottie/parsers/tgs.py
lib/lottie/parsers/aep/aep_riff.py
lib/lottie/parsers/aep/aepx.py
lib/lottie/parsers/aep/converter.py
lib/lottie/parsers/aep/cos.py
lib/lottie/parsers/aep/expressions.py
lib/lottie/parsers/aep/gradient_xml.py
